i129f/nvc_dhl_tracker/__init__.py
i129f/nvc_dhl_tracker/__main__.py
i129f/nvc_dhl_tracker/admin.py
i129f/nvc_dhl_tracker/apps.py
i129f/nvc_dhl_tracker/bot.py
i129f/nvc_dhl_tracker/cli.py
i129f/nvc_dhl_tracker/dhl.py
i129f/nvc_dhl_tracker/google.py
i129f/nvc_dhl_tracker/models.py
i129f/nvc_dhl_tracker/settings.py
i129f/nvc_dhl_tracker/tracker.py
i129f/nvc_dhl_tracker/views.py
i129f/nvc_dhl_tracker/management/__init__.py
i129f/nvc_dhl_tracker/management/commands/__init__.py
i129f/nvc_dhl_tracker/management/commands/run_nvc_tracker.py
i129f/nvc_dhl_tracker/migrations/0001_initial.py
i129f/nvc_dhl_tracker/migrations/0002_dhlpackage_dhlapikey_exhausted.py
i129f/nvc_dhl_tracker/migrations/0003_dhlpackage_origin.py
i129f/nvc_dhl_tracker/migrations/0004_alter_dhlpackage_discovered.py
i129f/nvc_dhl_tracker/migrations/0005_alter_dhlpackage_number.py
i129f/nvc_dhl_tracker/migrations/0006_alter_dhlpackage_became_delivered_and_more.py
i129f/nvc_dhl_tracker/migrations/__init__.py
i129f/nvc_dhl_tracker/signals/__init__.py
i129f/nvc_dhl_tracker/signals/receiver.py
i129f/nvc_dhl_tracker/signals/sender.py
nvc_dhl_tracker-0.1.15.dist-info/LICENSE.txt
nvc_dhl_tracker-0.1.15.dist-info/METADATA
nvc_dhl_tracker-0.1.15.dist-info/WHEEL
nvc_dhl_tracker-0.1.15.dist-info/entry_points.txt
nvc_dhl_tracker-0.1.15.dist-info/top_level.txt
nvc_dhl_tracker-0.1.15.dist-info/RECORD
