Metadata-Version: 2.1
Name: nvc-dhl-tracker
Version: 0.1.15
Summary: Automatically track and record records for NVC shipments!
Home-page: https://github.com/i129f-Scripts/nvc-dhl-tracker
Author: Collin Sage
Author-email: 3229549+MrSage@users.noreply.github.com
License: MIT
Project-URL: Documentation, https://pyscaffold.org/
Platform: any
Classifier: Development Status :: 4 - Beta
Classifier: Programming Language :: Python
License-File: LICENSE.txt
Requires-Dist: django
Requires-Dist: django-extensions
Requires-Dist: django-admin-autoregister
Requires-Dist: gspread
Requires-Dist: httpx
Requires-Dist: importlib-metadata ; python_version < "3.8"
Provides-Extra: testing
Requires-Dist: setuptools ; extra == 'testing'
Requires-Dist: pytest ; extra == 'testing'
Requires-Dist: pytest-cov ; extra == 'testing'
